istari_digital_client/__init__.py
istari_digital_client/api_client.py
istari_digital_client/api_response.py
istari_digital_client/client.py
istari_digital_client/configuration.py
istari_digital_client/env.py
istari_digital_client/exceptions.py
istari_digital_client/log_utils.py
istari_digital_client/py.typed
istari_digital_client/rest.py
istari_digital_client/storage/__init__.py
istari_digital_client/storage/api/__init__.py
istari_digital_client/storage/api/storage_api.py
istari_digital_client/storage/models/__init__.py
istari_digital_client/storage/models/completed_part_type_def.py
istari_digital_client/storage/models/create_multipart_upload_request.py
istari_digital_client/storage/models/create_multipart_upload_response.py
istari_digital_client/storage/models/finalize_multipart_upload_action.py
istari_digital_client/storage/models/finalize_multipart_upload_request.py
istari_digital_client/storage/models/http_validation_error.py
istari_digital_client/storage/models/page_tenant.py
istari_digital_client/storage/models/temporary_url.py
istari_digital_client/storage/models/tenant.py
istari_digital_client/storage/models/tenant_public_key.py
istari_digital_client/storage/models/validation_error.py
istari_digital_client/storage/models/validation_error_loc_inner.py
istari_digital_client/v2/__init__.py
istari_digital_client/v2/api/__init__.py
istari_digital_client/v2/api/v2_api.py
istari_digital_client/v2/models/__init__.py
istari_digital_client/v2/models/access_relation.py
istari_digital_client/v2/models/access_relationship.py
istari_digital_client/v2/models/access_resource_type.py
istari_digital_client/v2/models/access_subject_type.py
istari_digital_client/v2/models/agent.py
istari_digital_client/v2/models/agent_display_name.py
istari_digital_client/v2/models/agent_information.py
istari_digital_client/v2/models/agent_module_version.py
istari_digital_client/v2/models/agent_modules.py
istari_digital_client/v2/models/agent_pool.py
istari_digital_client-10.4.0.dist-info/METADATA
istari_digital_client-10.4.0.dist-info/WHEEL
istari_digital_client-10.4.0.dist-info/licenses/LICENSE
istari_digital_client-10.4.0.dist-info/RECORD
