Metadata-Version: 2.4
Name: istari-digital-client
Version: 10.4.0
Summary: Python client for the Istari Digital platform
License: MIT License
License-File: LICENSE
Author: Istari Digital Developers
Requires-Python: >=3.10,<4.0
Classifier: Environment :: Console
Classifier: Intended Audience :: Developers
Classifier: License :: OSI Approved :: MIT License
Classifier: Operating System :: OS Independent
Classifier: Programming Language :: Python :: 3
Classifier: Programming Language :: Python :: 3.10
Classifier: Programming Language :: Python :: 3.11
Classifier: Programming Language :: Python :: 3.12
Classifier: Programming Language :: Python :: 3.13
Classifier: Programming Language :: Python :: Implementation :: CPython
Requires-Dist: deprecation (>=2.1.0,<3.0.0)
Requires-Dist: inflection (>=0.5.1,<0.6.0)
Requires-Dist: istari-digital-core (==6.3.1)
Requires-Dist: pydantic (>=2.9.0,<3.0.0)
Requires-Dist: python-dateutil (>=2.9.0.post0,<3.0.0)
Requires-Dist: python-dotenv (>=1.0.1,<2.0.0)
Requires-Dist: types-python-dateutil (>=2.9.0.20240906,<3.0.0.0)
Requires-Dist: typing-extensions (>=4.12.2,<5.0.0)
Requires-Dist: urllib3 (>=2.6.0,<3.0.0)
Project-URL: Documentation, https://docs.istaridigital.com
Project-URL: Homepage, https://istaridigital.com
